intelx_identity.py
intelxapi.py
intelx-0.6.3.data/scripts/intelx.py
intelx-0.6.3.dist-info/METADATA
intelx-0.6.3.dist-info/WHEEL
intelx-0.6.3.dist-info/top_level.txt
intelx-0.6.3.dist-info/RECORD
