Metadata-Version: 2.1
Name: intelx
Version: 0.6.3
Summary: IntelX is a Python command-line utility and API wrapper for intelx.io, made to perform any kind of open-source intelligence.
Author-email: "Kleissner Investments s.r.o./ Dominik Penner" <info@intelx.io>
Project-URL: Bug Tracker, https://github.com/IntelligenceX/SDK/issues
Project-URL: Homepage, https://github.com/IntelligenceX/SDK/tree/master/Python
Keywords: IntelligenceX,_IntelligenceX,_intelx,intelligence x,intelx,intelx.io
Classifier: Operating System :: OS Independent
Classifier: Programming Language :: Python :: 3
Requires-Python: >=3.9
Requires-Dist: pygments
Requires-Dist: requests
Requires-Dist: tabulate
Requires-Dist: termcolor
